{
  "chest_001": {
    "externalId": "exr_41n2hxnFMotsXTj3",
    "externalName": "Bench Press",
    "thumbnail": "https://cqckuldmpmjpjqofmejt.supabase.co/storage/v1/object/public/exercises/thumbnails/chest_001.jpg",
    "videoUrl": null,
    "instructions": null
  },
  "chest_002": {
    "externalId": "exr_41n2hxnFMotsXTj3",
    "externalName": "Bench Press",
    "thumbnail": "https://cqckuldmpmjpjqofmejt.supabase.co/storage/v1/object/public/exercises/thumbnails/chest_002.jpg",
    "videoUrl": null,
    "instructions": null
  },
  "chest_003": {
    "externalId": "exr_41n2hxnFMotsXTj3",
    "externalName": "Bench Press",
    "thumbnail": "https://cqckuldmpmjpjqofmejt.supabase.co/storage/v1/object/public/exercises/thumbnails/chest_003.jpg",
    "videoUrl": null,
    "instructions": null
  },
  "chest_004": {
    "externalId": "exr_41n2hxnFMotsXTj3",
    "externalName": "Bench Press",
    "thumbnail": "https://cqckuldmpmjpjqofmejt.supabase.co/storage/v1/object/public/exercises/thumbnails/chest_004.jpg",
    "videoUrl": null,
    "instructions": null
  },
  "chest_005": {
    "externalId": "exr_41n2haNJ3NA8yCE2",
    "externalName": "Dumbbell Incline One Arm Hammer Press",
    "thumbnail": "https://cqckuldmpmjpjqofmejt.supabase.co/storage/v1/object/public/exercises/thumbnails/chest_005.jpg",
    "videoUrl": null,
    "instructions": null
  },
  "chest_006": {
    "externalId": "exr_41n2haNJ3NA8yCE2",
    "externalName": "Dumbbell Incline One Arm Hammer Press",
    "thumbnail": "https://cqckuldmpmjpjqofmejt.supabase.co/storage/v1/object/public/exercises/thumbnails/chest_006.jpg",
    "videoUrl": null,
    "instructions": null
  },
  "chest_007": {
    "externalId": "exr_41n2hyNf5GebszTf",
    "externalName": "Dumbbell Rear Delt Fly ",
    "thumbnail": "https://cqckuldmpmjpjqofmejt.supabase.co/storage/v1/object/public/exercises/thumbnails/chest_007.jpg",
    "videoUrl": null,
    "instructions": null
  },
  "chest_008": {
    "externalId": "exr_41n2haNJ3NA8yCE2",
    "externalName": "Dumbbell Incline One Arm Hammer Press",
    "thumbnail": "https://cqckuldmpmjpjqofmejt.supabase.co/storage/v1/object/public/exercises/thumbnails/chest_008.jpg",
    "videoUrl": null,
    "instructions": null
  },
  "chest_009": null,
  "chest_010": null,
  "chest_011": null,
  "chest_012": null,
  "chest_013": null,
  "chest_014": {
    "externalId": "exr_41n2hGUso7JFmuYR",
    "externalName": "Decline Push-Up",
    "thumbnail": "https://cqckuldmpmjpjqofmejt.supabase.co/storage/v1/object/public/exercises/thumbnails/chest_014.jpg",
    "videoUrl": null,
    "instructions": null
  },
  "chest_015": {
    "externalId": "exr_41n2hNXJadYcfjnd",
    "externalName": "Push-up",
    "thumbnail": "https://cqckuldmpmjpjqofmejt.supabase.co/storage/v1/object/public/exercises/thumbnails/chest_015.jpg",
    "videoUrl": null,
    "instructions": null
  },
  "chest_016": {
    "externalId": "exr_41n2hnbt5GwwY7gr",
    "externalName": "Diamond Push up ",
    "thumbnail": "https://cqckuldmpmjpjqofmejt.supabase.co/storage/v1/object/public/exercises/thumbnails/chest_016.jpg",
    "videoUrl": null,
    "instructions": null
  },
  "chest_017": null,
  "chest_018": null,
  "back_001": {
    "externalId": "exr_41n2hcw2FN534HcA",
    "externalName": "Dumbbell Stiff Leg Deadlift",
    "thumbnail": "https://cqckuldmpmjpjqofmejt.supabase.co/storage/v1/object/public/exercises/thumbnails/back_001.jpg",
    "videoUrl": null,
    "instructions": null
  },
  "back_002": {
    "externalId": "exr_41n2hn8rpbYihzEW",
    "externalName": "Romanian Deadlift",
    "thumbnail": "https://cqckuldmpmjpjqofmejt.supabase.co/storage/v1/object/public/exercises/thumbnails/back_002.jpg",
    "videoUrl": null,
    "instructions": null
  },
  "back_003": null,
  "back_004": null,
  "back_005": null,
  "back_006": {
    "externalId": "exr_41n2hftBVLiXgtRQ",
    "externalName": "Wide Grip Pull-Up",
    "thumbnail": "https://cqckuldmpmjpjqofmejt.supabase.co/storage/v1/object/public/exercises/thumbnails/back_006.jpg",
    "videoUrl": null,
    "instructions": null
  },
  "back_007": {
    "externalId": "exr_41n2hd6SThQhAdnZ",
    "externalName": "Chin-ups",
    "thumbnail": "https://cqckuldmpmjpjqofmejt.supabase.co/storage/v1/object/public/exercises/thumbnails/back_007.jpg",
    "videoUrl": null,
    "instructions": null
  },
  "back_008": {
    "externalId": "exr_41n2hsBtDXapcADg",
    "externalName": "Pull-up",
    "thumbnail": "https://cqckuldmpmjpjqofmejt.supabase.co/storage/v1/object/public/exercises/thumbnails/back_008.jpg",
    "videoUrl": null,
    "instructions": null
  },
  "back_009": null,
  "back_010": null,
  "back_011": {
    "externalId": "exr_41n2hcFJpBvAkXCP",
    "externalName": "Seated Row with Towel",
    "thumbnail": "https://cqckuldmpmjpjqofmejt.supabase.co/storage/v1/object/public/exercises/thumbnails/back_011.jpg",
    "videoUrl": null,
    "instructions": null
  },
  "back_012": null,
  "back_013": {
    "externalId": "exr_41n2hY9EdwkdGz9a",
    "externalName": "Dumbbell One Arm Bent-over Row",
    "thumbnail": "https://cqckuldmpmjpjqofmejt.supabase.co/storage/v1/object/public/exercises/thumbnails/back_013.jpg",
    "videoUrl": null,
    "instructions": null
  },
  "back_014": {
    "externalId": "exr_41n2haNJ3NA8yCE2",
    "externalName": "Dumbbell Incline One Arm Hammer Press",
    "thumbnail": "https://cqckuldmpmjpjqofmejt.supabase.co/storage/v1/object/public/exercises/thumbnails/back_014.jpg",
    "videoUrl": null,
    "instructions": null
  },
  "back_015": null,
  "back_016": null,
  "back_017": null,
  "back_018": null,
  "back_019": null,
  "sho_001": null,
  "sho_002": {
    "externalId": "exr_41n2haNJ3NA8yCE2",
    "externalName": "Dumbbell Incline One Arm Hammer Press",
    "thumbnail": "https://cqckuldmpmjpjqofmejt.supabase.co/storage/v1/object/public/exercises/thumbnails/sho_002.jpg",
    "videoUrl": null,
    "instructions": null
  },
  "sho_003": {
    "externalId": "exr_41n2hMRXm49mM62z",
    "externalName": "Arnold Press",
    "thumbnail": "https://cqckuldmpmjpjqofmejt.supabase.co/storage/v1/object/public/exercises/thumbnails/sho_003.jpg",
    "videoUrl": null,
    "instructions": null
  },
  "sho_004": {
    "externalId": "exr_41n2hjuGpcex14w7",
    "externalName": "Lateral Raise",
    "thumbnail": "https://cqckuldmpmjpjqofmejt.supabase.co/storage/v1/object/public/exercises/thumbnails/sho_004.jpg",
    "videoUrl": null,
    "instructions": null
  },
  "sho_005": {
    "externalId": "exr_41n2hjuGpcex14w7",
    "externalName": "Lateral Raise",
    "thumbnail": "https://cqckuldmpmjpjqofmejt.supabase.co/storage/v1/object/public/exercises/thumbnails/sho_005.jpg",
    "videoUrl": null,
    "instructions": null
  },
  "sho_006": {
    "externalId": "exr_41n2howQHvcrcrW6",
    "externalName": "Front Raise",
    "thumbnail": "https://cqckuldmpmjpjqofmejt.supabase.co/storage/v1/object/public/exercises/thumbnails/sho_006.jpg",
    "videoUrl": null,
    "instructions": null
  },
  "sho_007": {
    "externalId": "exr_41n2howQHvcrcrW6",
    "externalName": "Front Raise",
    "thumbnail": "https://cqckuldmpmjpjqofmejt.supabase.co/storage/v1/object/public/exercises/thumbnails/sho_007.jpg",
    "videoUrl": null,
    "instructions": null
  },
  "sho_008": null,
  "sho_009": {
    "externalId": "exr_41n2hyNf5GebszTf",
    "externalName": "Dumbbell Rear Delt Fly ",
    "thumbnail": "https://cqckuldmpmjpjqofmejt.supabase.co/storage/v1/object/public/exercises/thumbnails/sho_009.jpg",
    "videoUrl": null,
    "instructions": null
  },
  "sho_010": {
    "externalId": "exr_41n2hs6camM22yBG",
    "externalName": "Seated Shoulder Press",
    "thumbnail": "https://cqckuldmpmjpjqofmejt.supabase.co/storage/v1/object/public/exercises/thumbnails/sho_010.jpg",
    "videoUrl": null,
    "instructions": null
  },
  "sho_011": null,
  "sho_012": null,
  "sho_013": {
    "externalId": "exr_41n2hNXJadYcfjnd",
    "externalName": "Push-up",
    "thumbnail": "https://cqckuldmpmjpjqofmejt.supabase.co/storage/v1/object/public/exercises/thumbnails/sho_013.jpg",
    "videoUrl": null,
    "instructions": null
  },
  "sho_014": null,
  "sho_015": null,
  "arm_001": null,
  "arm_002": null,
  "arm_003": null,
  "arm_004": {
    "externalId": "exr_41n2hgCHNgtVLHna",
    "externalName": "Cross Body Hammer Curl",
    "thumbnail": "https://cqckuldmpmjpjqofmejt.supabase.co/storage/v1/object/public/exercises/thumbnails/arm_004.jpg",
    "videoUrl": null,
    "instructions": null
  },
  "arm_005": {
    "externalId": "exr_41n2haNJ3NA8yCE2",
    "externalName": "Dumbbell Incline One Arm Hammer Press",
    "thumbnail": "https://cqckuldmpmjpjqofmejt.supabase.co/storage/v1/object/public/exercises/thumbnails/arm_005.jpg",
    "videoUrl": null,
    "instructions": null
  },
  "arm_006": {
    "externalId": "exr_41n2hxqpSU5p6DZv",
    "externalName": "Biceps Leg Concentration Curl",
    "thumbnail": "https://cqckuldmpmjpjqofmejt.supabase.co/storage/v1/object/public/exercises/thumbnails/arm_006.jpg",
    "videoUrl": null,
    "instructions": null
  },
  "arm_007": null,
  "arm_008": null,
  "arm_009": null,
  "arm_010": null,
  "arm_011": null,
  "arm_012": null,
  "arm_013": null,
  "arm_014": {
    "externalId": "exr_41n2hxnFMotsXTj3",
    "externalName": "Bench Press",
    "thumbnail": "https://cqckuldmpmjpjqofmejt.supabase.co/storage/v1/object/public/exercises/thumbnails/arm_014.jpg",
    "videoUrl": null,
    "instructions": null
  },
  "arm_015": {
    "externalId": "exr_41n2hadQgEEX8wDN",
    "externalName": "Triceps Dip",
    "thumbnail": "https://cqckuldmpmjpjqofmejt.supabase.co/storage/v1/object/public/exercises/thumbnails/arm_015.jpg",
    "videoUrl": null,
    "instructions": null
  },
  "arm_016": null,
  "arm_017": {
    "externalId": "exr_41n2hGy6zE7fN6v2",
    "externalName": "One arm Wrist Curl",
    "thumbnail": "https://cqckuldmpmjpjqofmejt.supabase.co/storage/v1/object/public/exercises/thumbnails/arm_017.jpg",
    "videoUrl": null,
    "instructions": null
  },
  "arm_018": {
    "externalId": "exr_41n2hGy6zE7fN6v2",
    "externalName": "One arm Wrist Curl",
    "thumbnail": "https://cqckuldmpmjpjqofmejt.supabase.co/storage/v1/object/public/exercises/thumbnails/arm_018.jpg",
    "videoUrl": null,
    "instructions": null
  },
  "leg_001": {
    "externalId": "exr_41n2hmGR8WuVfe1U",
    "externalName": "Squat",
    "thumbnail": "https://cqckuldmpmjpjqofmejt.supabase.co/storage/v1/object/public/exercises/thumbnails/leg_001.jpg",
    "videoUrl": null,
    "instructions": null
  },
  "leg_002": {
    "externalId": "exr_41n2hmGR8WuVfe1U",
    "externalName": "Squat",
    "thumbnail": "https://cqckuldmpmjpjqofmejt.supabase.co/storage/v1/object/public/exercises/thumbnails/leg_002.jpg",
    "videoUrl": null,
    "instructions": null
  },
  "leg_003": {
    "externalId": "exr_41n2hmGR8WuVfe1U",
    "externalName": "Squat",
    "thumbnail": "https://cqckuldmpmjpjqofmejt.supabase.co/storage/v1/object/public/exercises/thumbnails/leg_003.jpg",
    "videoUrl": null,
    "instructions": null
  },
  "leg_004": {
    "externalId": "exr_41n2hmGR8WuVfe1U",
    "externalName": "Squat",
    "thumbnail": "https://cqckuldmpmjpjqofmejt.supabase.co/storage/v1/object/public/exercises/thumbnails/leg_004.jpg",
    "videoUrl": null,
    "instructions": null
  },
  "leg_005": {
    "externalId": "exr_41n2hmGR8WuVfe1U",
    "externalName": "Squat",
    "thumbnail": "https://cqckuldmpmjpjqofmejt.supabase.co/storage/v1/object/public/exercises/thumbnails/leg_005.jpg",
    "videoUrl": null,
    "instructions": null
  },
  "leg_006": null,
  "leg_007": null,
  "leg_008": {
    "externalId": "exr_41n2hPvwqp7Pwvks",
    "externalName": "Seated Single Leg Hamstring Stretch",
    "thumbnail": "https://cqckuldmpmjpjqofmejt.supabase.co/storage/v1/object/public/exercises/thumbnails/leg_008.jpg",
    "videoUrl": null,
    "instructions": null
  },
  "leg_009": {
    "externalId": "exr_41n2hc2VrB8ofxrW",
    "externalName": "Lying Double Legs Biceps Curl with Towel",
    "thumbnail": "https://cqckuldmpmjpjqofmejt.supabase.co/storage/v1/object/public/exercises/thumbnails/leg_009.jpg",
    "videoUrl": null,
    "instructions": null
  },
  "leg_010": {
    "externalId": "exr_41n2hn8rpbYihzEW",
    "externalName": "Romanian Deadlift",
    "thumbnail": "https://cqckuldmpmjpjqofmejt.supabase.co/storage/v1/object/public/exercises/thumbnails/leg_010.jpg",
    "videoUrl": null,
    "instructions": null
  },
  "leg_011": {
    "externalId": "exr_41n2hcw2FN534HcA",
    "externalName": "Dumbbell Stiff Leg Deadlift",
    "thumbnail": "https://cqckuldmpmjpjqofmejt.supabase.co/storage/v1/object/public/exercises/thumbnails/leg_011.jpg",
    "videoUrl": null,
    "instructions": null
  },
  "leg_012": {
    "externalId": "exr_41n2hQHmRSoUkk9F",
    "externalName": "Walking Lunge",
    "thumbnail": "https://cqckuldmpmjpjqofmejt.supabase.co/storage/v1/object/public/exercises/thumbnails/leg_012.jpg",
    "videoUrl": null,
    "instructions": null
  },
  "leg_013": {
    "externalId": "exr_41n2hGNrmUnF58Yy",
    "externalName": "Reverse Lunge ",
    "thumbnail": "https://cqckuldmpmjpjqofmejt.supabase.co/storage/v1/object/public/exercises/thumbnails/leg_013.jpg",
    "videoUrl": null,
    "instructions": null
  },
  "leg_014": null,
  "leg_015": null,
  "leg_016": {
    "externalId": "exr_41n2hWbP5uF6PQpU",
    "externalName": "Donkey Calf Raise",
    "thumbnail": "https://cqckuldmpmjpjqofmejt.supabase.co/storage/v1/object/public/exercises/thumbnails/leg_016.jpg",
    "videoUrl": null,
    "instructions": null
  },
  "leg_017": {
    "externalId": "exr_41n2hxxePSdr5oN1",
    "externalName": "Hip Thrusts",
    "thumbnail": "https://cqckuldmpmjpjqofmejt.supabase.co/storage/v1/object/public/exercises/thumbnails/leg_017.jpg",
    "videoUrl": null,
    "instructions": null
  },
  "leg_018": null,
  "leg_019": {
    "externalId": "exr_41n2hmGR8WuVfe1U",
    "externalName": "Squat",
    "thumbnail": "https://cqckuldmpmjpjqofmejt.supabase.co/storage/v1/object/public/exercises/thumbnails/leg_019.jpg",
    "videoUrl": null,
    "instructions": null
  },
  "leg_020": {
    "externalId": "exr_41n2hXvPyEyMBgNR",
    "externalName": "Step-up on Chair",
    "thumbnail": "https://cqckuldmpmjpjqofmejt.supabase.co/storage/v1/object/public/exercises/thumbnails/leg_020.jpg",
    "videoUrl": null,
    "instructions": null
  },
  "leg_021": null,
  "leg_022": {
    "externalId": "exr_41n2hmGR8WuVfe1U",
    "externalName": "Squat",
    "thumbnail": "https://cqckuldmpmjpjqofmejt.supabase.co/storage/v1/object/public/exercises/thumbnails/leg_022.jpg",
    "videoUrl": null,
    "instructions": null
  },
  "core_001": null,
  "core_002": null,
  "core_003": null,
  "core_004": {
    "externalId": "exr_41n2hskeb9dXgBoC",
    "externalName": "Crunch Floor",
    "thumbnail": "https://cqckuldmpmjpjqofmejt.supabase.co/storage/v1/object/public/exercises/thumbnails/core_004.jpg",
    "videoUrl": null,
    "instructions": null
  },
  "core_005": null,
  "core_006": null,
  "core_007": {
    "externalId": "exr_41n2hbLX4XH8xgN7",
    "externalName": "Dumbbell Single Leg Calf Raise",
    "thumbnail": "https://cqckuldmpmjpjqofmejt.supabase.co/storage/v1/object/public/exercises/thumbnails/core_007.jpg",
    "videoUrl": null,
    "instructions": null
  },
  "core_008": {
    "externalId": "exr_41n2hMZCmZBvQApL",
    "externalName": "Hanging Straight Leg Raise ",
    "thumbnail": "https://cqckuldmpmjpjqofmejt.supabase.co/storage/v1/object/public/exercises/thumbnails/core_008.jpg",
    "videoUrl": null,
    "instructions": null
  },
  "core_009": null,
  "core_010": {
    "externalId": "exr_41n2hvjrFJ2KjzGm",
    "externalName": "Sit ",
    "thumbnail": "https://cqckuldmpmjpjqofmejt.supabase.co/storage/v1/object/public/exercises/thumbnails/core_010.jpg",
    "videoUrl": null,
    "instructions": null
  },
  "core_011": {
    "externalId": "exr_41n2hWVVEwU54UtF",
    "externalName": "Russian Twist",
    "thumbnail": "https://cqckuldmpmjpjqofmejt.supabase.co/storage/v1/object/public/exercises/thumbnails/core_011.jpg",
    "videoUrl": null,
    "instructions": null
  },
  "core_012": null,
  "core_013": null,
  "core_014": null,
  "core_015": null,
  "core_016": null,
  "core_017": null,
  "core_018": null,
  "core_019": null,
  "core_020": null,
  "oly_001": null,
  "oly_002": null,
  "oly_003": null,
  "oly_004": null,
  "oly_005": null,
  "oly_006": null,
  "oly_007": null,
  "fb_001": null,
  "fb_002": null,
  "fb_003": null,
  "fb_004": {
    "externalId": "exr_41n2hqYdxG87hXz1",
    "externalName": "Burpee",
    "thumbnail": "https://cqckuldmpmjpjqofmejt.supabase.co/storage/v1/object/public/exercises/thumbnails/fb_004.jpg",
    "videoUrl": null,
    "instructions": null
  },
  "fb_005": null,
  "fb_006": null,
  "fb_007": null,
  "fb_008": null,
  "fb_009": null,
  "fb_010": null,
  "card_001": null,
  "card_002": null,
  "card_003": null,
  "card_004": null,
  "card_005": null,
  "card_006": {
    "externalId": "exr_41n2hLZZAH2F2UkS",
    "externalName": "Walk Elliptical Cross Trainer ",
    "thumbnail": "https://cqckuldmpmjpjqofmejt.supabase.co/storage/v1/object/public/exercises/thumbnails/card_006.jpg",
    "videoUrl": null,
    "instructions": null
  },
  "card_007": null,
  "card_008": {
    "externalId": "exr_41n2hN468sP27Sac",
    "externalName": "Jump Rope",
    "thumbnail": "https://cqckuldmpmjpjqofmejt.supabase.co/storage/v1/object/public/exercises/thumbnails/card_008.jpg",
    "videoUrl": null,
    "instructions": null
  },
  "card_009": null,
  "card_010": null,
  "card_011": {
    "externalId": "exr_41n2hmhb4jD7H8Qk",
    "externalName": "Assault Bike Run",
    "thumbnail": "https://cqckuldmpmjpjqofmejt.supabase.co/storage/v1/object/public/exercises/thumbnails/card_011.jpg",
    "videoUrl": null,
    "instructions": null
  },
  "card_012": null,
  "card_013": {
    "externalId": "exr_41n2hupxPcdnktBC",
    "externalName": "Jumping Jack",
    "thumbnail": "https://cqckuldmpmjpjqofmejt.supabase.co/storage/v1/object/public/exercises/thumbnails/card_013.jpg",
    "videoUrl": null,
    "instructions": null
  },
  "card_014": {
    "externalId": "exr_41n2ha5iPFpN3hEJ",
    "externalName": "Bridge - Mountain Climber ",
    "thumbnail": "https://cqckuldmpmjpjqofmejt.supabase.co/storage/v1/object/public/exercises/thumbnails/card_014.jpg",
    "videoUrl": null,
    "instructions": null
  },
  "card_015": null
}